{"chunk_definitions":[{"row":38,"row_count":1,"visible":true,"expansion_state":0,"options":{"engine":"r","label":"dlSampleData","echo":true},"document_id":"D48DBDAA","chunk_id":"ckqsnlj2elmho","chunk_label":"dlSampleData"},{"row":73,"row_count":1,"visible":true,"expansion_state":0,"options":{},"document_id":"D48DBDAA","chunk_id":"cesvy6kcas91f","chunk_label":"ImportFullDat"},{"row":92,"row_count":1,"visible":true,"expansion_state":0,"options":{},"document_id":"D48DBDAA","chunk_id":"cfmypg0by5ylt","chunk_label":"Convert"},{"row":101,"row_count":1,"visible":true,"expansion_state":0,"options":{},"document_id":"D48DBDAA","chunk_id":"cvolw28u3irp4","chunk_label":"FirstParticle"},{"row":136,"row_count":1,"visible":true,"expansion_state":0,"options":{},"document_id":"D48DBDAA","chunk_id":"cwc5tymbmxl7a","chunk_label":"Drawfrags1"},{"row":167,"row_count":1,"visible":true,"expansion_state":0,"options":{},"document_id":"D48DBDAA","chunk_id":"cqqnxegd63drq","chunk_label":"Drawfrags2"}],"doc_write_time":1676644691}